qurpc/__init__.py
qurpc/bencoder.py
qurpc/client.py
qurpc/exceptions.py
qurpc/kad.py
qurpc/kcp.py
qurpc/rpc.py
qurpc/serialize.py
qurpc/server.py
qurpc/utils.py
qurpc/version.py
QuLab_RPC-2.2.6.dist-info/LICENSE
QuLab_RPC-2.2.6.dist-info/METADATA
QuLab_RPC-2.2.6.dist-info/WHEEL
QuLab_RPC-2.2.6.dist-info/top_level.txt
QuLab_RPC-2.2.6.dist-info/RECORD
